{
    "Ax": {
        "error": 1.9643949381000524e-07,
        "error_type": "SEM",
        "filter_outliers_dict": {
            "filter_outliers": false,
            "iterations": 1,
            "std_devs": 2
        },
        "fit": "average",
        "value": -0.00019521375489773413
    },
    "H2": {
        "error": 1.5907346103890453e-07,
        "error_type": "SEM",
        "filter_outliers_dict": {
            "filter_outliers": true,
            "iterations": 1,
            "std_devs": 2
        },
        "fit": "average",
        "value": -0.00027438750879823305
    },
    "H4": {
        "error": 1.8206880811583406e-07,
        "error_type": "SEM",
        "filter_outliers_dict": {
            "filter_outliers": true,
            "iterations": 1,
            "std_devs": 2
        },
        "fit": "average",
        "value": -7.62431827137931e-05
    },
    "L2": {
        "error": 1.7971265345949137e-07,
        "error_type": "SEM",
        "filter_outliers_dict": {
            "filter_outliers": true,
            "iterations": 1,
            "std_devs": 2
        },
        "fit": "average",
        "value": -2.281010711779339e-05
    },
    "L4": {
        "error": 2.9445969742897195e-10,
        "error_type": "SEM",
        "filter_outliers_dict": {
            "filter_outliers": false,
            "iterations": 1,
            "std_devs": 2
        },
        "fit": "average",
        "value": 1.3866666666666673e-09
    }
}